worldnewsapi/__init__.py
worldnewsapi/api_client.py
worldnewsapi/api_response.py
worldnewsapi/configuration.py
worldnewsapi/exceptions.py
worldnewsapi/py.typed
worldnewsapi/rest.py
worldnewsapi/api/__init__.py
worldnewsapi/api/news_api.py
worldnewsapi/models/__init__.py
worldnewsapi/models/extract_news200_response.py
worldnewsapi/models/extract_news200_response_images_inner.py
worldnewsapi/models/extract_news200_response_videos_inner.py
worldnewsapi/models/extract_news_links200_response.py
worldnewsapi/models/get_geo_coordinates200_response.py
worldnewsapi/models/retrieve_news_articles_by_ids200_response.py
worldnewsapi/models/retrieve_news_articles_by_ids200_response_news_inner.py
worldnewsapi/models/retrieve_newspaper_front_page200_response.py
worldnewsapi/models/retrieve_newspaper_front_page200_response_front_page.py
worldnewsapi/models/search_news200_response.py
worldnewsapi/models/search_news200_response_news_inner.py
worldnewsapi/models/search_news_sources200_response.py
worldnewsapi/models/search_news_sources200_response_sources_inner.py
worldnewsapi/models/top_news200_response.py
worldnewsapi/models/top_news200_response_top_news_inner.py
worldnewsapi/models/top_news200_response_top_news_inner_news_inner.py
worldnewsapi-2.2.0.dist-info/METADATA
worldnewsapi-2.2.0.dist-info/WHEEL
worldnewsapi-2.2.0.dist-info/top_level.txt
worldnewsapi-2.2.0.dist-info/RECORD
