Metadata-Version: 2.1
Name: worldnewsapi
Version: 2.2.0
Summary: The world's news wrapped into a single API.
Home-page: 
Author: David Urbansky
Author-email: David Urbansky <mail@worldnewsapi.com>
Project-URL: Homepage, https://worldnewsapi.com
Project-URL: Documentation, https://worldnewsapi.com/docs
Project-URL: Repository, https://github.com/ddsky/world-news-api-clients/tree/main/python
Project-URL: Bug Tracker, https://github.com/ddsky/world-news-api-clients/issues
Keywords: OpenAPI,OpenAPI-Generator,World News API
Classifier: Programming Language :: Python :: 3
Classifier: License :: OSI Approved :: MIT License
Classifier: Operating System :: OS Independent
Requires-Python: >=3.7
Requires-Dist: urllib3 <2.1.0,>=1.25.3
Requires-Dist: python-dateutil
Requires-Dist: pydantic >=2
Requires-Dist: typing-extensions >=4.7.1
